{
  "sections": [
    {
      "is_dynamic": false,
      "title": "About Us",
      "url": "/about",
      "target": false
    },
    {
      "is_dynamic": true,
      "title": "Careers",
      "url": "/careers",
      "target": false
    },
    {
      "is_dynamic": false,
      "title": "Privacy Policy",
      "url": "/privacy-policy",
      "target": false
    },
    {
      "is_dynamic": false,
      "title": "Source Code",
      "url": "https://github.com/claudiovallejo/materiales-vallejo",
      "target": true
    }
  ]
}
